project_is_even/__init__.py
project_is_even/cli.py
project_is_even/is_even_module.py
project_is_even-0.1.0.dist-info/METADATA
project_is_even-0.1.0.dist-info/WHEEL
project_is_even-0.1.0.dist-info/entry_points.txt
project_is_even-0.1.0.dist-info/RECORD
