Metadata-Version: 2.1
Name: project-is-even
Version: 0.1.0
Summary: 
Author: Cicero98
Requires-Python: >=3.10,<3.11
Classifier: Programming Language :: Python :: 3
Classifier: Programming Language :: Python :: 3.10
Requires-Dist: click (>=8.1.7,<9.0.0)
Requires-Dist: numpy (>=1.26.3,<2.0.0)
